huaweicloudsdkswr/__init__.py
huaweicloudsdkswr/v2/__init__.py
huaweicloudsdkswr/v2/swr_async_client.py
huaweicloudsdkswr/v2/swr_client.py
huaweicloudsdkswr/v2/model/__init__.py
huaweicloudsdkswr/v2/model/accessory.py
huaweicloudsdkswr/v2/model/accessory_list_accessories.py
huaweicloudsdkswr/v2/model/add_domain_name_request.py
huaweicloudsdkswr/v2/model/add_domain_name_request_body.py
huaweicloudsdkswr/v2/model/add_domain_name_response.py
huaweicloudsdkswr/v2/model/artifact.py
huaweicloudsdkswr/v2/model/artifact_tag.py
huaweicloudsdkswr/v2/model/audit_log.py
huaweicloudsdkswr/v2/model/auth_info.py
huaweicloudsdkswr/v2/model/auth_token.py
huaweicloudsdkswr/v2/model/build_history.py
huaweicloudsdkswr/v2/model/check_agency_request.py
huaweicloudsdkswr/v2/model/check_agency_response.py
huaweicloudsdkswr/v2/model/create_agency_request.py
huaweicloudsdkswr/v2/model/create_agency_response.py
huaweicloudsdkswr/v2/model/create_authorization_token_request.py
huaweicloudsdkswr/v2/model/create_authorization_token_response.py
huaweicloudsdkswr/v2/model/create_endpoint_policy_request_body.py
huaweicloudsdkswr/v2/model/create_image_sync_repo_request.py
huaweicloudsdkswr/v2/model/create_image_sync_repo_request_body.py
huaweicloudsdkswr/v2/model/create_image_sync_repo_response.py
huaweicloudsdkswr/v2/model/create_immutable_rule_body.py
huaweicloudsdkswr/v2/model/create_immutable_rule_request.py
huaweicloudsdkswr/v2/model/create_immutable_rule_response.py
huaweicloudsdkswr/v2/model/create_instance_endpoint_policy_request.py
huaweicloudsdkswr/v2/model/create_instance_endpoint_policy_response.py
huaweicloudsdkswr/v2/model/create_instance_internal_endpoint_request.py
huaweicloudsdkswr/v2/model/create_instance_internal_endpoint_response.py
huaweicloudsdkswr/v2/model/create_instance_lt_credential_request.py
huaweicloudsdkswr/v2/model/create_instance_lt_credential_response.py
huaweicloudsdkswr/v2/model/create_instance_namespace_request.py
huaweicloudsdkswr-3.1.184.dist-info/METADATA
huaweicloudsdkswr-3.1.184.dist-info/WHEEL
huaweicloudsdkswr-3.1.184.dist-info/licenses/LICENSE
huaweicloudsdkswr-3.1.184.dist-info/RECORD
